.gitignore
CHANGES.txt
LICENSE
MANIFEST.in
README.rst
requirements.txt
runtests.py
setup.py
tox.ini
extras/README.rst
extras/memegen.py
meme/__init__.py
meme/meme.py
meme.egg-info/PKG-INFO
meme.egg-info/SOURCES.txt
meme.egg-info/dependency_links.txt
meme.egg-info/entry_points.txt
meme.egg-info/requires.txt
meme.egg-info/top_level.txt
meme/tests/__init__.py
meme/tests/action_result.json
meme/tests/info.json
meme/tests/popular.json
meme/tests/search.json
meme/tests/test_meme.py